sftpclient/__init__.py
sftpclient-1.0.0.dist-info/LICENSE.txt
sftpclient-1.0.0.dist-info/METADATA
sftpclient-1.0.0.dist-info/WHEEL
sftpclient-1.0.0.dist-info/top_level.txt
sftpclient-1.0.0.dist-info/RECORD
