Metadata-Version: 2.1
Name: sftpclient
Version: 1.0.0
Summary: Username/Password SFTP Client
Home-page: https://github.com/yankyhoffman/sftpclient.git
Author: Yanky Hoffman
Author-email: developer.yankyhoffman@gmail.com
License: UNKNOWN
Platform: UNKNOWN
Requires-Dist: pysftp
